apitools/__init__.py
apitools/clients/__init__.py
apitools/clients/bigquery/__init__.py
apitools/clients/bigquery/bigquery_v2_client.py
apitools/clients/bigquery/bigquery_v2_messages.py
google_apitools_bigquery_v2-0.4.20150731.dist-info/DESCRIPTION.rst
google_apitools_bigquery_v2-0.4.20150731.dist-info/METADATA
google_apitools_bigquery_v2-0.4.20150731.dist-info/metadata.json
google_apitools_bigquery_v2-0.4.20150731.dist-info/RECORD
google_apitools_bigquery_v2-0.4.20150731.dist-info/top_level.txt
google_apitools_bigquery_v2-0.4.20150731.dist-info/WHEEL
